{
  "_meta": {
    "category": "Beauty Tech",
    "total": 2
  },
  "products": [
    {
      "id": "xiaomi-hair-dryer-h101",
      "name": "Xiaomi Compact Hair Dryer H101",
      "price": 249000,
      "category": "Beauty Tech",
      "subcategory": "Hair Dryer",
      "platform": "shopee",
      "link": "https://s.shopee.co.id/9paP5SjBjj"
    },
    {
      "id": "infinix-hair-dryer-pengering-rambut-64db-ultra-sil",
      "name": "Infinix Hair Dryer | Pengering Rambut - 64db Ultra Silence - High Speed Drying - Smart Temperature Control - Magnetic Nozzle - Dust Proof",
      "price": 329000,
      "category": "Beauty Tech",
      "subcategory": "Hair Dryer",
      "platform": "shopee",
      "link": "https://s.shopee.co.id/2g7GArsUJE"
    }
  ]
}